[{
  "_id": {
    "$oid": "62a887a619cacf3ab907126b"
  },
  "index": 1,
  "name": "Indret",
  "state": true,
  "screen": 1,
  "temperature": 51.002,
  "__v": 0,
  "bug": false,
  "door_1": false,
  "door_2": false,
  "online": true,
  "isOpen": false
},{
  "_id": {
    "$oid": "62a887b119cacf3ab907126d"
  },
  "index": 2,
  "name": "UB Aval",
  "state": true,
  "screen": 0,
  "temperature": 55.017,
  "__v": 0,
  "bug": false,
  "door_1": false,
  "door_2": false,
  "online": true
},{
  "_id": {
    "$oid": "62a887b519cacf3ab907126f"
  },
  "index": 3,
  "name": "UB Amont",
  "state": true,
  "screen": 1,
  "temperature": 40.78,
  "__v": 0,
  "bug": false,
  "door_1": false,
  "door_2": false,
  "online": true
}]